{
  "type" : "Aadl",
  "components" : [
    {
      "type" : "Component",
      "identifier" : {
        "type" : "Name",
        "name" : ["tcs"],
        "pos" : {
          "type" : "Some",
          "value" : {
            "type" : "Position",
            "uriOpt" : {
              "type" : "Some",
              "value" : "\/temp-control\/TempControlAadl.sysml"
            },
            "beginLine" : 11,
            "beginColumn" : 2,
            "endLine" : 14,
            "endColumn" : 3,
            "offset" : 226,
            "length" : 103
          }
        }
      },
      "category" : {
        "type" : "ComponentCategory",
        "value" : "System"
      },
      "classifier" : {
        "type" : "Some",
        "value" : {
          "type" : "Classifier",
          "name" : "TempControlAadl::TempControlSystem"
        }
      },
      "features" : [
      ],
      "subComponents" : [
        {
          "type" : "Component",
          "identifier" : {
            "type" : "Name",
            "name" : ["tcs", "tcp"],
            "pos" : {
              "type" : "Some",
              "value" : {
                "type" : "Position",
                "uriOpt" : {
                  "type" : "Some",
                  "value" : "\/temp-control\/TempControlAadl.sysml"
                },
                "beginLine" : 16,
                "beginColumn" : 2,
                "endLine" : 30,
                "endColumn" : 3,
                "offset" : 333,
                "length" : 759
              }
            }
          },
          "category" : {
            "type" : "ComponentCategory",
            "value" : "Process"
          },
          "classifier" : {
            "type" : "Some",
            "value" : {
              "type" : "Classifier",
              "name" : "TempControlAadl::TempControlProcess"
            }
          },
          "features" : [
          ],
          "subComponents" : [
            {
              "type" : "Component",
              "identifier" : {
                "type" : "Name",
                "name" : ["tcs", "tcp", "tempSensor"],
                "pos" : {
                  "type" : "Some",
                  "value" : {
                    "type" : "Position",
                    "uriOpt" : {
                      "type" : "Some",
                      "value" : "\/temp-control\/TempControlAadl.sysml"
                    },
                    "beginLine" : 33,
                    "beginColumn" : 2,
                    "endLine" : 44,
                    "endColumn" : 3,
                    "offset" : 1118,
                    "length" : 206
                  }
                }
              },
              "category" : {
                "type" : "ComponentCategory",
                "value" : "Thread"
              },
              "classifier" : {
                "type" : "Some",
                "value" : {
                  "type" : "Classifier",
                  "name" : "TempControlAadl::TempSensor"
                }
              },
              "features" : [
                {
                  "type" : "FeatureEnd",
                  "identifier" : {
                    "type" : "Name",
                    "name" : ["tcs", "tcp", "tempSensor", "ports_currentTemp"],
                    "pos" : {
                      "type" : "None"
                    }
                  },
                  "direction" : {
                    "type" : "Direction",
                    "value" : "Out"
                  },
                  "category" : {
                    "type" : "FeatureCategory",
                    "value" : "DataPort"
                  },
                  "classifier" : {
                    "type" : "Some",
                    "value" : {
                      "type" : "Classifier",
                      "name" : "TempControlAadl::Temperature"
                    }
                  },
                  "properties" : [
                  ],
                  "uriFrag" : "fake uri tag that's only needed if AWAS is invoked"
                },
                {
                  "type" : "FeatureEnd",
                  "identifier" : {
                    "type" : "Name",
                    "name" : ["tcs", "tcp", "tempSensor", "ports_tempChanged"],
                    "pos" : {
                      "type" : "None"
                    }
                  },
                  "direction" : {
                    "type" : "Direction",
                    "value" : "Out"
                  },
                  "category" : {
                    "type" : "FeatureCategory",
                    "value" : "EventPort"
                  },
                  "classifier" : {
                    "type" : "None"
                  },
                  "properties" : [
                  ],
                  "uriFrag" : "fake uri tag that's only needed if AWAS is invoked"
                }
              ],
              "subComponents" : [
              ],
              "connections" : [
              ],
              "connectionInstances" : [
              ],
              "properties" : [
                {
                  "type" : "Property",
                  "name" : {
                    "type" : "Name",
                    "name" : ["tcs", "tcp", "tempSensor", "Thread_Properties::Dispatch_Protocol"],
                    "pos" : {
                      "type" : "Some",
                      "value" : {
                        "type" : "Position",
                        "uriOpt" : {
                          "type" : "Some",
                          "value" : "\/aadl.contributions\/AADLProperties.sysml"
                        },
                        "beginLine" : 11,
                        "beginColumn" : 3,
                        "endLine" : 11,
                        "endColumn" : 62,
                        "offset" : 323,
                        "length" : 59
                      }
                    }
                  },
                  "propertyValues" : [
                    {
                      "type" : "ValueProp",
                      "value" : "Periodic"
                    }
                  ],
                  "appliesTo" : [
                  ]
                },
                {
                  "type" : "Property",
                  "name" : {
                    "type" : "Name",
                    "name" : ["tcs", "tcp", "tempSensor", "Timing_Properties::Period"],
                    "pos" : {
                      "type" : "Some",
                      "value" : {
                        "type" : "Position",
                        "uriOpt" : {
                          "type" : "Some",
                          "value" : "\/aadl.contributions\/AADLProperties.sysml"
                        },
                        "beginLine" : 16,
                        "beginColumn" : 3,
                        "endLine" : 16,
                        "endColumn" : 44,
                        "offset" : 449,
                        "length" : 41
                      }
                    }
                  },
                  "propertyValues" : [
                    {
                      "type" : "UnitProp",
                      "value" : "1.0E12",
                      "unit" : {
                        "type" : "Some",
                        "value" : "ps"
                      }
                    }
                  ],
                  "appliesTo" : [
                  ]
                }
              ],
              "flows" : [
              ],
              "modes" : [
              ],
              "annexes" : [
              ],
              "uriFrag" : ""
            },
            {
              "type" : "Component",
              "identifier" : {
                "type" : "Name",
                "name" : ["tcs", "tcp", "tempControl"],
                "pos" : {
                  "type" : "Some",
                  "value" : {
                    "type" : "Position",
                    "uriOpt" : {
                      "type" : "Some",
                      "value" : "\/temp-control\/TempControlAadl.sysml"
                    },
                    "beginLine" : 47,
                    "beginColumn" : 2,
                    "endLine" : 61,
                    "endColumn" : 3,
                    "offset" : 1350,
                    "length" : 313
                  }
                }
              },
              "category" : {
                "type" : "ComponentCategory",
                "value" : "Thread"
              },
              "classifier" : {
                "type" : "Some",
                "value" : {
                  "type" : "Classifier",
                  "name" : "TempControlAadl::TempControl"
                }
              },
              "features" : [
                {
                  "type" : "FeatureEnd",
                  "identifier" : {
                    "type" : "Name",
                    "name" : ["tcs", "tcp", "tempControl", "ports_currentTemp"],
                    "pos" : {
                      "type" : "None"
                    }
                  },
                  "direction" : {
                    "type" : "Direction",
                    "value" : "In"
                  },
                  "category" : {
                    "type" : "FeatureCategory",
                    "value" : "DataPort"
                  },
                  "classifier" : {
                    "type" : "Some",
                    "value" : {
                      "type" : "Classifier",
                      "name" : "TempControlAadl::Temperature"
                    }
                  },
                  "properties" : [
                  ],
                  "uriFrag" : "fake uri tag that's only needed if AWAS is invoked"
                },
                {
                  "type" : "FeatureEnd",
                  "identifier" : {
                    "type" : "Name",
                    "name" : ["tcs", "tcp", "tempControl", "ports_tempChanged"],
                    "pos" : {
                      "type" : "None"
                    }
                  },
                  "direction" : {
                    "type" : "Direction",
                    "value" : "In"
                  },
                  "category" : {
                    "type" : "FeatureCategory",
                    "value" : "EventPort"
                  },
                  "classifier" : {
                    "type" : "None"
                  },
                  "properties" : [
                  ],
                  "uriFrag" : "fake uri tag that's only needed if AWAS is invoked"
                },
                {
                  "type" : "FeatureEnd",
                  "identifier" : {
                    "type" : "Name",
                    "name" : ["tcs", "tcp", "tempControl", "ports_fanCmd"],
                    "pos" : {
                      "type" : "None"
                    }
                  },
                  "direction" : {
                    "type" : "Direction",
                    "value" : "Out"
                  },
                  "category" : {
                    "type" : "FeatureCategory",
                    "value" : "EventDataPort"
                  },
                  "classifier" : {
                    "type" : "Some",
                    "value" : {
                      "type" : "Classifier",
                      "name" : "TempControlAadl::FanCmd"
                    }
                  },
                  "properties" : [
                  ],
                  "uriFrag" : "fake uri tag that's only needed if AWAS is invoked"
                },
                {
                  "type" : "FeatureEnd",
                  "identifier" : {
                    "type" : "Name",
                    "name" : ["tcs", "tcp", "tempControl", "ports_fanAck"],
                    "pos" : {
                      "type" : "None"
                    }
                  },
                  "direction" : {
                    "type" : "Direction",
                    "value" : "In"
                  },
                  "category" : {
                    "type" : "FeatureCategory",
                    "value" : "EventDataPort"
                  },
                  "classifier" : {
                    "type" : "Some",
                    "value" : {
                      "type" : "Classifier",
                      "name" : "TempControlAadl::FanAck"
                    }
                  },
                  "properties" : [
                  ],
                  "uriFrag" : "fake uri tag that's only needed if AWAS is invoked"
                },
                {
                  "type" : "FeatureEnd",
                  "identifier" : {
                    "type" : "Name",
                    "name" : ["tcs", "tcp", "tempControl", "ports_setPoint"],
                    "pos" : {
                      "type" : "None"
                    }
                  },
                  "direction" : {
                    "type" : "Direction",
                    "value" : "In"
                  },
                  "category" : {
                    "type" : "FeatureCategory",
                    "value" : "EventDataPort"
                  },
                  "classifier" : {
                    "type" : "Some",
                    "value" : {
                      "type" : "Classifier",
                      "name" : "TempControlAadl::Temperature"
                    }
                  },
                  "properties" : [
                  ],
                  "uriFrag" : "fake uri tag that's only needed if AWAS is invoked"
                }
              ],
              "subComponents" : [
              ],
              "connections" : [
              ],
              "connectionInstances" : [
              ],
              "properties" : [
                {
                  "type" : "Property",
                  "name" : {
                    "type" : "Name",
                    "name" : ["tcs", "tcp", "tempControl", "Thread_Properties::Dispatch_Protocol"],
                    "pos" : {
                      "type" : "Some",
                      "value" : {
                        "type" : "Position",
                        "uriOpt" : {
                          "type" : "Some",
                          "value" : "\/aadl.contributions\/AADLProperties.sysml"
                        },
                        "beginLine" : 11,
                        "beginColumn" : 3,
                        "endLine" : 11,
                        "endColumn" : 62,
                        "offset" : 323,
                        "length" : 59
                      }
                    }
                  },
                  "propertyValues" : [
                    {
                      "type" : "ValueProp",
                      "value" : "Sporadic"
                    }
                  ],
                  "appliesTo" : [
                  ]
                },
                {
                  "type" : "Property",
                  "name" : {
                    "type" : "Name",
                    "name" : ["tcs", "tcp", "tempControl", "Timing_Properties::Period"],
                    "pos" : {
                      "type" : "Some",
                      "value" : {
                        "type" : "Position",
                        "uriOpt" : {
                          "type" : "Some",
                          "value" : "\/aadl.contributions\/AADLProperties.sysml"
                        },
                        "beginLine" : 16,
                        "beginColumn" : 3,
                        "endLine" : 16,
                        "endColumn" : 44,
                        "offset" : 449,
                        "length" : 41
                      }
                    }
                  },
                  "propertyValues" : [
                    {
                      "type" : "UnitProp",
                      "value" : "1.0E12",
                      "unit" : {
                        "type" : "Some",
                        "value" : "ps"
                      }
                    }
                  ],
                  "appliesTo" : [
                  ]
                }
              ],
              "flows" : [
              ],
              "modes" : [
              ],
              "annexes" : [
              ],
              "uriFrag" : ""
            },
            {
              "type" : "Component",
              "identifier" : {
                "type" : "Name",
                "name" : ["tcs", "tcp", "fan"],
                "pos" : {
                  "type" : "Some",
                  "value" : {
                    "type" : "Position",
                    "uriOpt" : {
                      "type" : "Some",
                      "value" : "\/temp-control\/TempControlAadl.sysml"
                    },
                    "beginLine" : 64,
                    "beginColumn" : 2,
                    "endLine" : 75,
                    "endColumn" : 3,
                    "offset" : 1681,
                    "length" : 201
                  }
                }
              },
              "category" : {
                "type" : "ComponentCategory",
                "value" : "Thread"
              },
              "classifier" : {
                "type" : "Some",
                "value" : {
                  "type" : "Classifier",
                  "name" : "TempControlAadl::Fan"
                }
              },
              "features" : [
                {
                  "type" : "FeatureEnd",
                  "identifier" : {
                    "type" : "Name",
                    "name" : ["tcs", "tcp", "fan", "ports_fanCmd"],
                    "pos" : {
                      "type" : "None"
                    }
                  },
                  "direction" : {
                    "type" : "Direction",
                    "value" : "In"
                  },
                  "category" : {
                    "type" : "FeatureCategory",
                    "value" : "EventDataPort"
                  },
                  "classifier" : {
                    "type" : "Some",
                    "value" : {
                      "type" : "Classifier",
                      "name" : "TempControlAadl::FanCmd"
                    }
                  },
                  "properties" : [
                  ],
                  "uriFrag" : "fake uri tag that's only needed if AWAS is invoked"
                },
                {
                  "type" : "FeatureEnd",
                  "identifier" : {
                    "type" : "Name",
                    "name" : ["tcs", "tcp", "fan", "ports_fanAck"],
                    "pos" : {
                      "type" : "None"
                    }
                  },
                  "direction" : {
                    "type" : "Direction",
                    "value" : "Out"
                  },
                  "category" : {
                    "type" : "FeatureCategory",
                    "value" : "EventDataPort"
                  },
                  "classifier" : {
                    "type" : "Some",
                    "value" : {
                      "type" : "Classifier",
                      "name" : "TempControlAadl::FanAck"
                    }
                  },
                  "properties" : [
                  ],
                  "uriFrag" : "fake uri tag that's only needed if AWAS is invoked"
                }
              ],
              "subComponents" : [
              ],
              "connections" : [
              ],
              "connectionInstances" : [
              ],
              "properties" : [
                {
                  "type" : "Property",
                  "name" : {
                    "type" : "Name",
                    "name" : ["tcs", "tcp", "fan", "Thread_Properties::Dispatch_Protocol"],
                    "pos" : {
                      "type" : "Some",
                      "value" : {
                        "type" : "Position",
                        "uriOpt" : {
                          "type" : "Some",
                          "value" : "\/aadl.contributions\/AADLProperties.sysml"
                        },
                        "beginLine" : 11,
                        "beginColumn" : 3,
                        "endLine" : 11,
                        "endColumn" : 62,
                        "offset" : 323,
                        "length" : 59
                      }
                    }
                  },
                  "propertyValues" : [
                    {
                      "type" : "ValueProp",
                      "value" : "Sporadic"
                    }
                  ],
                  "appliesTo" : [
                  ]
                },
                {
                  "type" : "Property",
                  "name" : {
                    "type" : "Name",
                    "name" : ["tcs", "tcp", "fan", "Timing_Properties::Period"],
                    "pos" : {
                      "type" : "Some",
                      "value" : {
                        "type" : "Position",
                        "uriOpt" : {
                          "type" : "Some",
                          "value" : "\/aadl.contributions\/AADLProperties.sysml"
                        },
                        "beginLine" : 16,
                        "beginColumn" : 3,
                        "endLine" : 16,
                        "endColumn" : 44,
                        "offset" : 449,
                        "length" : 41
                      }
                    }
                  },
                  "propertyValues" : [
                    {
                      "type" : "UnitProp",
                      "value" : "1.0E12",
                      "unit" : {
                        "type" : "Some",
                        "value" : "ps"
                      }
                    }
                  ],
                  "appliesTo" : [
                  ]
                }
              ],
              "flows" : [
              ],
              "modes" : [
              ],
              "annexes" : [
              ],
              "uriFrag" : ""
            },
            {
              "type" : "Component",
              "identifier" : {
                "type" : "Name",
                "name" : ["tcs", "tcp", "opInterface"],
                "pos" : {
                  "type" : "Some",
                  "value" : {
                    "type" : "Position",
                    "uriOpt" : {
                      "type" : "Some",
                      "value" : "\/temp-control\/TempControlAadl.sysml"
                    },
                    "beginLine" : 78,
                    "beginColumn" : 2,
                    "endLine" : 89,
                    "endColumn" : 3,
                    "offset" : 1914,
                    "length" : 226
                  }
                }
              },
              "category" : {
                "type" : "ComponentCategory",
                "value" : "Thread"
              },
              "classifier" : {
                "type" : "Some",
                "value" : {
                  "type" : "Classifier",
                  "name" : "TempControlAadl::OperatorInterface"
                }
              },
              "features" : [
                {
                  "type" : "FeatureEnd",
                  "identifier" : {
                    "type" : "Name",
                    "name" : ["tcs", "tcp", "opInterface", "ports_currentTemp"],
                    "pos" : {
                      "type" : "None"
                    }
                  },
                  "direction" : {
                    "type" : "Direction",
                    "value" : "In"
                  },
                  "category" : {
                    "type" : "FeatureCategory",
                    "value" : "DataPort"
                  },
                  "classifier" : {
                    "type" : "Some",
                    "value" : {
                      "type" : "Classifier",
                      "name" : "TempControlAadl::Temperature"
                    }
                  },
                  "properties" : [
                  ],
                  "uriFrag" : "fake uri tag that's only needed if AWAS is invoked"
                },
                {
                  "type" : "FeatureEnd",
                  "identifier" : {
                    "type" : "Name",
                    "name" : ["tcs", "tcp", "opInterface", "ports_setPoint"],
                    "pos" : {
                      "type" : "None"
                    }
                  },
                  "direction" : {
                    "type" : "Direction",
                    "value" : "Out"
                  },
                  "category" : {
                    "type" : "FeatureCategory",
                    "value" : "EventDataPort"
                  },
                  "classifier" : {
                    "type" : "Some",
                    "value" : {
                      "type" : "Classifier",
                      "name" : "TempControlAadl::Temperature"
                    }
                  },
                  "properties" : [
                  ],
                  "uriFrag" : "fake uri tag that's only needed if AWAS is invoked"
                }
              ],
              "subComponents" : [
              ],
              "connections" : [
              ],
              "connectionInstances" : [
              ],
              "properties" : [
                {
                  "type" : "Property",
                  "name" : {
                    "type" : "Name",
                    "name" : ["tcs", "tcp", "opInterface", "Thread_Properties::Dispatch_Protocol"],
                    "pos" : {
                      "type" : "Some",
                      "value" : {
                        "type" : "Position",
                        "uriOpt" : {
                          "type" : "Some",
                          "value" : "\/aadl.contributions\/AADLProperties.sysml"
                        },
                        "beginLine" : 11,
                        "beginColumn" : 3,
                        "endLine" : 11,
                        "endColumn" : 62,
                        "offset" : 323,
                        "length" : 59
                      }
                    }
                  },
                  "propertyValues" : [
                    {
                      "type" : "ValueProp",
                      "value" : "Periodic"
                    }
                  ],
                  "appliesTo" : [
                  ]
                },
                {
                  "type" : "Property",
                  "name" : {
                    "type" : "Name",
                    "name" : ["tcs", "tcp", "opInterface", "Timing_Properties::Period"],
                    "pos" : {
                      "type" : "Some",
                      "value" : {
                        "type" : "Position",
                        "uriOpt" : {
                          "type" : "Some",
                          "value" : "\/aadl.contributions\/AADLProperties.sysml"
                        },
                        "beginLine" : 16,
                        "beginColumn" : 3,
                        "endLine" : 16,
                        "endColumn" : 44,
                        "offset" : 449,
                        "length" : 41
                      }
                    }
                  },
                  "propertyValues" : [
                    {
                      "type" : "UnitProp",
                      "value" : "1.0E12",
                      "unit" : {
                        "type" : "Some",
                        "value" : "ps"
                      }
                    }
                  ],
                  "appliesTo" : [
                  ]
                }
              ],
              "flows" : [
              ],
              "modes" : [
              ],
              "annexes" : [
              ],
              "uriFrag" : ""
            }
          ],
          "connections" : [
            {
              "type" : "Connection",
              "name" : {
                "type" : "Name",
                "name" : ["tcs", "tcp", "ctTStoTC"],
                "pos" : {
                  "type" : "Some",
                  "value" : {
                    "type" : "Position",
                    "uriOpt" : {
                      "type" : "Some",
                      "value" : "\/temp-control\/TempControlAadl.sysml"
                    },
                    "beginLine" : 24,
                    "beginColumn" : 3,
                    "endLine" : 24,
                    "endColumn" : 93,
                    "offset" : 575,
                    "length" : 90
                  }
                }
              },
              "src" : [
                {
                  "type" : "EndPoint",
                  "component" : {
                    "type" : "Name",
                    "name" : ["tcs", "tcp", "tempSensor"],
                    "pos" : {
                      "type" : "Some",
                      "value" : {
                        "type" : "Position",
                        "uriOpt" : {
                          "type" : "Some",
                          "value" : "\/temp-control\/TempControlAadl.sysml"
                        },
                        "beginLine" : 18,
                        "beginColumn" : 3,
                        "endLine" : 18,
                        "endColumn" : 41,
                        "offset" : 395,
                        "length" : 38
                      }
                    }
                  },
                  "feature" : {
                    "type" : "Some",
                    "value" : {
                      "type" : "Name",
                      "name" : ["tcs", "tcp", "tempSensor", "ports_currentTemp"],
                      "pos" : {
                        "type" : "Some",
                        "value" : {
                          "type" : "Position",
                          "uriOpt" : {
                            "type" : "Some",
                            "value" : "\/temp-control\/TempControlAadl.sysml"
                          },
                          "beginLine" : 36,
                          "beginColumn" : 4,
                          "endLine" : 36,
                          "endColumn" : 39,
                          "offset" : 1181,
                          "length" : 35
                        }
                      }
                    }
                  },
                  "direction" : {
                    "type" : "Some",
                    "value" : {
                      "type" : "Direction",
                      "value" : "Out"
                    }
                  }
                }
              ],
              "dst" : [
                {
                  "type" : "EndPoint",
                  "component" : {
                    "type" : "Name",
                    "name" : ["tcs", "tcp", "tempControl"],
                    "pos" : {
                      "type" : "Some",
                      "value" : {
                        "type" : "Position",
                        "uriOpt" : {
                          "type" : "Some",
                          "value" : "\/temp-control\/TempControlAadl.sysml"
                        },
                        "beginLine" : 19,
                        "beginColumn" : 3,
                        "endLine" : 19,
                        "endColumn" : 43,
                        "offset" : 436,
                        "length" : 40
                      }
                    }
                  },
                  "feature" : {
                    "type" : "Some",
                    "value" : {
                      "type" : "Name",
                      "name" : ["tcs", "tcp", "tempControl", "ports_currentTemp"],
                      "pos" : {
                        "type" : "Some",
                        "value" : {
                          "type" : "Position",
                          "uriOpt" : {
                            "type" : "Some",
                            "value" : "\/temp-control\/TempControlAadl.sysml"
                          },
                          "beginLine" : 50,
                          "beginColumn" : 4,
                          "endLine" : 50,
                          "endColumn" : 38,
                          "offset" : 1415,
                          "length" : 34
                        }
                      }
                    }
                  },
                  "direction" : {
                    "type" : "Some",
                    "value" : {
                      "type" : "Direction",
                      "value" : "In"
                    }
                  }
                }
              ],
              "kind" : {
                "type" : "ConnectionKind",
                "value" : "Port"
              },
              "isBiDirectional" : false,
              "connectionInstances" : [
              ],
              "properties" : [
              ],
              "uriFrag" : "fake uri tag that's only needed if AWAS is invoked"
            },
            {
              "type" : "Connection",
              "name" : {
                "type" : "Name",
                "name" : ["tcs", "tcp", "ctTStoOI"],
                "pos" : {
                  "type" : "Some",
                  "value" : {
                    "type" : "Position",
                    "uriOpt" : {
                      "type" : "Some",
                      "value" : "\/temp-control\/TempControlAadl.sysml"
                    },
                    "beginLine" : 25,
                    "beginColumn" : 3,
                    "endLine" : 25,
                    "endColumn" : 93,
                    "offset" : 668,
                    "length" : 90
                  }
                }
              },
              "src" : [
                {
                  "type" : "EndPoint",
                  "component" : {
                    "type" : "Name",
                    "name" : ["tcs", "tcp", "tempSensor"],
                    "pos" : {
                      "type" : "Some",
                      "value" : {
                        "type" : "Position",
                        "uriOpt" : {
                          "type" : "Some",
                          "value" : "\/temp-control\/TempControlAadl.sysml"
                        },
                        "beginLine" : 18,
                        "beginColumn" : 3,
                        "endLine" : 18,
                        "endColumn" : 41,
                        "offset" : 395,
                        "length" : 38
                      }
                    }
                  },
                  "feature" : {
                    "type" : "Some",
                    "value" : {
                      "type" : "Name",
                      "name" : ["tcs", "tcp", "tempSensor", "ports_currentTemp"],
                      "pos" : {
                        "type" : "Some",
                        "value" : {
                          "type" : "Position",
                          "uriOpt" : {
                            "type" : "Some",
                            "value" : "\/temp-control\/TempControlAadl.sysml"
                          },
                          "beginLine" : 36,
                          "beginColumn" : 4,
                          "endLine" : 36,
                          "endColumn" : 39,
                          "offset" : 1181,
                          "length" : 35
                        }
                      }
                    }
                  },
                  "direction" : {
                    "type" : "Some",
                    "value" : {
                      "type" : "Direction",
                      "value" : "Out"
                    }
                  }
                }
              ],
              "dst" : [
                {
                  "type" : "EndPoint",
                  "component" : {
                    "type" : "Name",
                    "name" : ["tcs", "tcp", "opInterface"],
                    "pos" : {
                      "type" : "Some",
                      "value" : {
                        "type" : "Position",
                        "uriOpt" : {
                          "type" : "Some",
                          "value" : "\/temp-control\/TempControlAadl.sysml"
                        },
                        "beginLine" : 21,
                        "beginColumn" : 3,
                        "endLine" : 21,
                        "endColumn" : 49,
                        "offset" : 506,
                        "length" : 46
                      }
                    }
                  },
                  "feature" : {
                    "type" : "Some",
                    "value" : {
                      "type" : "Name",
                      "name" : ["tcs", "tcp", "opInterface", "ports_currentTemp"],
                      "pos" : {
                        "type" : "Some",
                        "value" : {
                          "type" : "Position",
                          "uriOpt" : {
                            "type" : "Some",
                            "value" : "\/temp-control\/TempControlAadl.sysml"
                          },
                          "beginLine" : 81,
                          "beginColumn" : 4,
                          "endLine" : 81,
                          "endColumn" : 38,
                          "offset" : 1985,
                          "length" : 34
                        }
                      }
                    }
                  },
                  "direction" : {
                    "type" : "Some",
                    "value" : {
                      "type" : "Direction",
                      "value" : "In"
                    }
                  }
                }
              ],
              "kind" : {
                "type" : "ConnectionKind",
                "value" : "Port"
              },
              "isBiDirectional" : false,
              "connectionInstances" : [
              ],
              "properties" : [
              ],
              "uriFrag" : "fake uri tag that's only needed if AWAS is invoked"
            },
            {
              "type" : "Connection",
              "name" : {
                "type" : "Name",
                "name" : ["tcs", "tcp", "tcTStoTC"],
                "pos" : {
                  "type" : "Some",
                  "value" : {
                    "type" : "Position",
                    "uriOpt" : {
                      "type" : "Some",
                      "value" : "\/temp-control\/TempControlAadl.sysml"
                    },
                    "beginLine" : 26,
                    "beginColumn" : 3,
                    "endLine" : 26,
                    "endColumn" : 93,
                    "offset" : 761,
                    "length" : 90
                  }
                }
              },
              "src" : [
                {
                  "type" : "EndPoint",
                  "component" : {
                    "type" : "Name",
                    "name" : ["tcs", "tcp", "tempSensor"],
                    "pos" : {
                      "type" : "Some",
                      "value" : {
                        "type" : "Position",
                        "uriOpt" : {
                          "type" : "Some",
                          "value" : "\/temp-control\/TempControlAadl.sysml"
                        },
                        "beginLine" : 18,
                        "beginColumn" : 3,
                        "endLine" : 18,
                        "endColumn" : 41,
                        "offset" : 395,
                        "length" : 38
                      }
                    }
                  },
                  "feature" : {
                    "type" : "Some",
                    "value" : {
                      "type" : "Name",
                      "name" : ["tcs", "tcp", "tempSensor", "ports_tempChanged"],
                      "pos" : {
                        "type" : "Some",
                        "value" : {
                          "type" : "Position",
                          "uriOpt" : {
                            "type" : "Some",
                            "value" : "\/temp-control\/TempControlAadl.sysml"
                          },
                          "beginLine" : 37,
                          "beginColumn" : 4,
                          "endLine" : 37,
                          "endColumn" : 27,
                          "offset" : 1220,
                          "length" : 23
                        }
                      }
                    }
                  },
                  "direction" : {
                    "type" : "Some",
                    "value" : {
                      "type" : "Direction",
                      "value" : "Out"
                    }
                  }
                }
              ],
              "dst" : [
                {
                  "type" : "EndPoint",
                  "component" : {
                    "type" : "Name",
                    "name" : ["tcs", "tcp", "tempControl"],
                    "pos" : {
                      "type" : "Some",
                      "value" : {
                        "type" : "Position",
                        "uriOpt" : {
                          "type" : "Some",
                          "value" : "\/temp-control\/TempControlAadl.sysml"
                        },
                        "beginLine" : 19,
                        "beginColumn" : 3,
                        "endLine" : 19,
                        "endColumn" : 43,
                        "offset" : 436,
                        "length" : 40
                      }
                    }
                  },
                  "feature" : {
                    "type" : "Some",
                    "value" : {
                      "type" : "Name",
                      "name" : ["tcs", "tcp", "tempControl", "ports_tempChanged"],
                      "pos" : {
                        "type" : "Some",
                        "value" : {
                          "type" : "Position",
                          "uriOpt" : {
                            "type" : "Some",
                            "value" : "\/temp-control\/TempControlAadl.sysml"
                          },
                          "beginLine" : 51,
                          "beginColumn" : 4,
                          "endLine" : 51,
                          "endColumn" : 26,
                          "offset" : 1453,
                          "length" : 22
                        }
                      }
                    }
                  },
                  "direction" : {
                    "type" : "Some",
                    "value" : {
                      "type" : "Direction",
                      "value" : "In"
                    }
                  }
                }
              ],
              "kind" : {
                "type" : "ConnectionKind",
                "value" : "Port"
              },
              "isBiDirectional" : false,
              "connectionInstances" : [
              ],
              "properties" : [
              ],
              "uriFrag" : "fake uri tag that's only needed if AWAS is invoked"
            },
            {
              "type" : "Connection",
              "name" : {
                "type" : "Name",
                "name" : ["tcs", "tcp", "fcTCtoF"],
                "pos" : {
                  "type" : "Some",
                  "value" : {
                    "type" : "Position",
                    "uriOpt" : {
                      "type" : "Some",
                      "value" : "\/temp-control\/TempControlAadl.sysml"
                    },
                    "beginLine" : 27,
                    "beginColumn" : 3,
                    "endLine" : 27,
                    "endColumn" : 75,
                    "offset" : 854,
                    "length" : 72
                  }
                }
              },
              "src" : [
                {
                  "type" : "EndPoint",
                  "component" : {
                    "type" : "Name",
                    "name" : ["tcs", "tcp", "tempControl"],
                    "pos" : {
                      "type" : "Some",
                      "value" : {
                        "type" : "Position",
                        "uriOpt" : {
                          "type" : "Some",
                          "value" : "\/temp-control\/TempControlAadl.sysml"
                        },
                        "beginLine" : 19,
                        "beginColumn" : 3,
                        "endLine" : 19,
                        "endColumn" : 43,
                        "offset" : 436,
                        "length" : 40
                      }
                    }
                  },
                  "feature" : {
                    "type" : "Some",
                    "value" : {
                      "type" : "Name",
                      "name" : ["tcs", "tcp", "tempControl", "ports_fanCmd"],
                      "pos" : {
                        "type" : "Some",
                        "value" : {
                          "type" : "Position",
                          "uriOpt" : {
                            "type" : "Some",
                            "value" : "\/temp-control\/TempControlAadl.sysml"
                          },
                          "beginLine" : 52,
                          "beginColumn" : 4,
                          "endLine" : 52,
                          "endColumn" : 34,
                          "offset" : 1479,
                          "length" : 30
                        }
                      }
                    }
                  },
                  "direction" : {
                    "type" : "Some",
                    "value" : {
                      "type" : "Direction",
                      "value" : "Out"
                    }
                  }
                }
              ],
              "dst" : [
                {
                  "type" : "EndPoint",
                  "component" : {
                    "type" : "Name",
                    "name" : ["tcs", "tcp", "fan"],
                    "pos" : {
                      "type" : "Some",
                      "value" : {
                        "type" : "Position",
                        "uriOpt" : {
                          "type" : "Some",
                          "value" : "\/temp-control\/TempControlAadl.sysml"
                        },
                        "beginLine" : 20,
                        "beginColumn" : 3,
                        "endLine" : 20,
                        "endColumn" : 27,
                        "offset" : 479,
                        "length" : 24
                      }
                    }
                  },
                  "feature" : {
                    "type" : "Some",
                    "value" : {
                      "type" : "Name",
                      "name" : ["tcs", "tcp", "fan", "ports_fanCmd"],
                      "pos" : {
                        "type" : "Some",
                        "value" : {
                          "type" : "Position",
                          "uriOpt" : {
                            "type" : "Some",
                            "value" : "\/temp-control\/TempControlAadl.sysml"
                          },
                          "beginLine" : 67,
                          "beginColumn" : 4,
                          "endLine" : 67,
                          "endColumn" : 33,
                          "offset" : 1738,
                          "length" : 29
                        }
                      }
                    }
                  },
                  "direction" : {
                    "type" : "Some",
                    "value" : {
                      "type" : "Direction",
                      "value" : "In"
                    }
                  }
                }
              ],
              "kind" : {
                "type" : "ConnectionKind",
                "value" : "Port"
              },
              "isBiDirectional" : false,
              "connectionInstances" : [
              ],
              "properties" : [
              ],
              "uriFrag" : "fake uri tag that's only needed if AWAS is invoked"
            },
            {
              "type" : "Connection",
              "name" : {
                "type" : "Name",
                "name" : ["tcs", "tcp", "faFtoTC"],
                "pos" : {
                  "type" : "Some",
                  "value" : {
                    "type" : "Position",
                    "uriOpt" : {
                      "type" : "Some",
                      "value" : "\/temp-control\/TempControlAadl.sysml"
                    },
                    "beginLine" : 28,
                    "beginColumn" : 3,
                    "endLine" : 28,
                    "endColumn" : 75,
                    "offset" : 929,
                    "length" : 72
                  }
                }
              },
              "src" : [
                {
                  "type" : "EndPoint",
                  "component" : {
                    "type" : "Name",
                    "name" : ["tcs", "tcp", "fan"],
                    "pos" : {
                      "type" : "Some",
                      "value" : {
                        "type" : "Position",
                        "uriOpt" : {
                          "type" : "Some",
                          "value" : "\/temp-control\/TempControlAadl.sysml"
                        },
                        "beginLine" : 20,
                        "beginColumn" : 3,
                        "endLine" : 20,
                        "endColumn" : 27,
                        "offset" : 479,
                        "length" : 24
                      }
                    }
                  },
                  "feature" : {
                    "type" : "Some",
                    "value" : {
                      "type" : "Name",
                      "name" : ["tcs", "tcp", "fan", "ports_fanAck"],
                      "pos" : {
                        "type" : "Some",
                        "value" : {
                          "type" : "Position",
                          "uriOpt" : {
                            "type" : "Some",
                            "value" : "\/temp-control\/TempControlAadl.sysml"
                          },
                          "beginLine" : 68,
                          "beginColumn" : 4,
                          "endLine" : 68,
                          "endColumn" : 34,
                          "offset" : 1771,
                          "length" : 30
                        }
                      }
                    }
                  },
                  "direction" : {
                    "type" : "Some",
                    "value" : {
                      "type" : "Direction",
                      "value" : "Out"
                    }
                  }
                }
              ],
              "dst" : [
                {
                  "type" : "EndPoint",
                  "component" : {
                    "type" : "Name",
                    "name" : ["tcs", "tcp", "tempControl"],
                    "pos" : {
                      "type" : "Some",
                      "value" : {
                        "type" : "Position",
                        "uriOpt" : {
                          "type" : "Some",
                          "value" : "\/temp-control\/TempControlAadl.sysml"
                        },
                        "beginLine" : 19,
                        "beginColumn" : 3,
                        "endLine" : 19,
                        "endColumn" : 43,
                        "offset" : 436,
                        "length" : 40
                      }
                    }
                  },
                  "feature" : {
                    "type" : "Some",
                    "value" : {
                      "type" : "Name",
                      "name" : ["tcs", "tcp", "tempControl", "ports_fanAck"],
                      "pos" : {
                        "type" : "Some",
                        "value" : {
                          "type" : "Position",
                          "uriOpt" : {
                            "type" : "Some",
                            "value" : "\/temp-control\/TempControlAadl.sysml"
                          },
                          "beginLine" : 53,
                          "beginColumn" : 4,
                          "endLine" : 53,
                          "endColumn" : 33,
                          "offset" : 1513,
                          "length" : 29
                        }
                      }
                    }
                  },
                  "direction" : {
                    "type" : "Some",
                    "value" : {
                      "type" : "Direction",
                      "value" : "In"
                    }
                  }
                }
              ],
              "kind" : {
                "type" : "ConnectionKind",
                "value" : "Port"
              },
              "isBiDirectional" : false,
              "connectionInstances" : [
              ],
              "properties" : [
              ],
              "uriFrag" : "fake uri tag that's only needed if AWAS is invoked"
            },
            {
              "type" : "Connection",
              "name" : {
                "type" : "Name",
                "name" : ["tcs", "tcp", "spOItoTC"],
                "pos" : {
                  "type" : "Some",
                  "value" : {
                    "type" : "Position",
                    "uriOpt" : {
                      "type" : "Some",
                      "value" : "\/temp-control\/TempControlAadl.sysml"
                    },
                    "beginLine" : 29,
                    "beginColumn" : 3,
                    "endLine" : 29,
                    "endColumn" : 88,
                    "offset" : 1004,
                    "length" : 85
                  }
                }
              },
              "src" : [
                {
                  "type" : "EndPoint",
                  "component" : {
                    "type" : "Name",
                    "name" : ["tcs", "tcp", "opInterface"],
                    "pos" : {
                      "type" : "Some",
                      "value" : {
                        "type" : "Position",
                        "uriOpt" : {
                          "type" : "Some",
                          "value" : "\/temp-control\/TempControlAadl.sysml"
                        },
                        "beginLine" : 21,
                        "beginColumn" : 3,
                        "endLine" : 21,
                        "endColumn" : 49,
                        "offset" : 506,
                        "length" : 46
                      }
                    }
                  },
                  "feature" : {
                    "type" : "Some",
                    "value" : {
                      "type" : "Name",
                      "name" : ["tcs", "tcp", "opInterface", "ports_setPoint"],
                      "pos" : {
                        "type" : "Some",
                        "value" : {
                          "type" : "Position",
                          "uriOpt" : {
                            "type" : "Some",
                            "value" : "\/temp-control\/TempControlAadl.sysml"
                          },
                          "beginLine" : 82,
                          "beginColumn" : 4,
                          "endLine" : 82,
                          "endColumn" : 41,
                          "offset" : 2023,
                          "length" : 37
                        }
                      }
                    }
                  },
                  "direction" : {
                    "type" : "Some",
                    "value" : {
                      "type" : "Direction",
                      "value" : "Out"
                    }
                  }
                }
              ],
              "dst" : [
                {
                  "type" : "EndPoint",
                  "component" : {
                    "type" : "Name",
                    "name" : ["tcs", "tcp", "tempControl"],
                    "pos" : {
                      "type" : "Some",
                      "value" : {
                        "type" : "Position",
                        "uriOpt" : {
                          "type" : "Some",
                          "value" : "\/temp-control\/TempControlAadl.sysml"
                        },
                        "beginLine" : 19,
                        "beginColumn" : 3,
                        "endLine" : 19,
                        "endColumn" : 43,
                        "offset" : 436,
                        "length" : 40
                      }
                    }
                  },
                  "feature" : {
                    "type" : "Some",
                    "value" : {
                      "type" : "Name",
                      "name" : ["tcs", "tcp", "tempControl", "ports_setPoint"],
                      "pos" : {
                        "type" : "Some",
                        "value" : {
                          "type" : "Position",
                          "uriOpt" : {
                            "type" : "Some",
                            "value" : "\/temp-control\/TempControlAadl.sysml"
                          },
                          "beginLine" : 54,
                          "beginColumn" : 4,
                          "endLine" : 54,
                          "endColumn" : 40,
                          "offset" : 1546,
                          "length" : 36
                        }
                      }
                    }
                  },
                  "direction" : {
                    "type" : "Some",
                    "value" : {
                      "type" : "Direction",
                      "value" : "In"
                    }
                  }
                }
              ],
              "kind" : {
                "type" : "ConnectionKind",
                "value" : "Port"
              },
              "isBiDirectional" : false,
              "connectionInstances" : [
              ],
              "properties" : [
              ],
              "uriFrag" : "fake uri tag that's only needed if AWAS is invoked"
            }
          ],
          "connectionInstances" : [
            {
              "type" : "ConnectionInstance",
              "name" : {
                "type" : "Name",
                "name" : ["fake_it"],
                "pos" : {
                  "type" : "None"
                }
              },
              "src" : {
                "type" : "EndPoint",
                "component" : {
                  "type" : "Name",
                  "name" : ["tcs", "tcp", "tempSensor"],
                  "pos" : {
                    "type" : "Some",
                    "value" : {
                      "type" : "Position",
                      "uriOpt" : {
                        "type" : "Some",
                        "value" : "\/temp-control\/TempControlAadl.sysml"
                      },
                      "beginLine" : 18,
                      "beginColumn" : 3,
                      "endLine" : 18,
                      "endColumn" : 41,
                      "offset" : 395,
                      "length" : 38
                    }
                  }
                },
                "feature" : {
                  "type" : "Some",
                  "value" : {
                    "type" : "Name",
                    "name" : ["tcs", "tcp", "tempSensor", "ports_currentTemp"],
                    "pos" : {
                      "type" : "Some",
                      "value" : {
                        "type" : "Position",
                        "uriOpt" : {
                          "type" : "Some",
                          "value" : "\/temp-control\/TempControlAadl.sysml"
                        },
                        "beginLine" : 36,
                        "beginColumn" : 4,
                        "endLine" : 36,
                        "endColumn" : 39,
                        "offset" : 1181,
                        "length" : 35
                      }
                    }
                  }
                },
                "direction" : {
                  "type" : "Some",
                  "value" : {
                    "type" : "Direction",
                    "value" : "Out"
                  }
                }
              },
              "dst" : {
                "type" : "EndPoint",
                "component" : {
                  "type" : "Name",
                  "name" : ["tcs", "tcp", "tempControl"],
                  "pos" : {
                    "type" : "Some",
                    "value" : {
                      "type" : "Position",
                      "uriOpt" : {
                        "type" : "Some",
                        "value" : "\/temp-control\/TempControlAadl.sysml"
                      },
                      "beginLine" : 19,
                      "beginColumn" : 3,
                      "endLine" : 19,
                      "endColumn" : 43,
                      "offset" : 436,
                      "length" : 40
                    }
                  }
                },
                "feature" : {
                  "type" : "Some",
                  "value" : {
                    "type" : "Name",
                    "name" : ["tcs", "tcp", "tempControl", "ports_currentTemp"],
                    "pos" : {
                      "type" : "Some",
                      "value" : {
                        "type" : "Position",
                        "uriOpt" : {
                          "type" : "Some",
                          "value" : "\/temp-control\/TempControlAadl.sysml"
                        },
                        "beginLine" : 50,
                        "beginColumn" : 4,
                        "endLine" : 50,
                        "endColumn" : 38,
                        "offset" : 1415,
                        "length" : 34
                      }
                    }
                  }
                },
                "direction" : {
                  "type" : "Some",
                  "value" : {
                    "type" : "Direction",
                    "value" : "In"
                  }
                }
              },
              "kind" : {
                "type" : "ConnectionKind",
                "value" : "Port"
              },
              "connectionRefs" : [
              ],
              "properties" : [
              ]
            },
            {
              "type" : "ConnectionInstance",
              "name" : {
                "type" : "Name",
                "name" : ["fake_it"],
                "pos" : {
                  "type" : "None"
                }
              },
              "src" : {
                "type" : "EndPoint",
                "component" : {
                  "type" : "Name",
                  "name" : ["tcs", "tcp", "tempSensor"],
                  "pos" : {
                    "type" : "Some",
                    "value" : {
                      "type" : "Position",
                      "uriOpt" : {
                        "type" : "Some",
                        "value" : "\/temp-control\/TempControlAadl.sysml"
                      },
                      "beginLine" : 18,
                      "beginColumn" : 3,
                      "endLine" : 18,
                      "endColumn" : 41,
                      "offset" : 395,
                      "length" : 38
                    }
                  }
                },
                "feature" : {
                  "type" : "Some",
                  "value" : {
                    "type" : "Name",
                    "name" : ["tcs", "tcp", "tempSensor", "ports_currentTemp"],
                    "pos" : {
                      "type" : "Some",
                      "value" : {
                        "type" : "Position",
                        "uriOpt" : {
                          "type" : "Some",
                          "value" : "\/temp-control\/TempControlAadl.sysml"
                        },
                        "beginLine" : 36,
                        "beginColumn" : 4,
                        "endLine" : 36,
                        "endColumn" : 39,
                        "offset" : 1181,
                        "length" : 35
                      }
                    }
                  }
                },
                "direction" : {
                  "type" : "Some",
                  "value" : {
                    "type" : "Direction",
                    "value" : "Out"
                  }
                }
              },
              "dst" : {
                "type" : "EndPoint",
                "component" : {
                  "type" : "Name",
                  "name" : ["tcs", "tcp", "opInterface"],
                  "pos" : {
                    "type" : "Some",
                    "value" : {
                      "type" : "Position",
                      "uriOpt" : {
                        "type" : "Some",
                        "value" : "\/temp-control\/TempControlAadl.sysml"
                      },
                      "beginLine" : 21,
                      "beginColumn" : 3,
                      "endLine" : 21,
                      "endColumn" : 49,
                      "offset" : 506,
                      "length" : 46
                    }
                  }
                },
                "feature" : {
                  "type" : "Some",
                  "value" : {
                    "type" : "Name",
                    "name" : ["tcs", "tcp", "opInterface", "ports_currentTemp"],
                    "pos" : {
                      "type" : "Some",
                      "value" : {
                        "type" : "Position",
                        "uriOpt" : {
                          "type" : "Some",
                          "value" : "\/temp-control\/TempControlAadl.sysml"
                        },
                        "beginLine" : 81,
                        "beginColumn" : 4,
                        "endLine" : 81,
                        "endColumn" : 38,
                        "offset" : 1985,
                        "length" : 34
                      }
                    }
                  }
                },
                "direction" : {
                  "type" : "Some",
                  "value" : {
                    "type" : "Direction",
                    "value" : "In"
                  }
                }
              },
              "kind" : {
                "type" : "ConnectionKind",
                "value" : "Port"
              },
              "connectionRefs" : [
              ],
              "properties" : [
              ]
            },
            {
              "type" : "ConnectionInstance",
              "name" : {
                "type" : "Name",
                "name" : ["fake_it"],
                "pos" : {
                  "type" : "None"
                }
              },
              "src" : {
                "type" : "EndPoint",
                "component" : {
                  "type" : "Name",
                  "name" : ["tcs", "tcp", "tempSensor"],
                  "pos" : {
                    "type" : "Some",
                    "value" : {
                      "type" : "Position",
                      "uriOpt" : {
                        "type" : "Some",
                        "value" : "\/temp-control\/TempControlAadl.sysml"
                      },
                      "beginLine" : 18,
                      "beginColumn" : 3,
                      "endLine" : 18,
                      "endColumn" : 41,
                      "offset" : 395,
                      "length" : 38
                    }
                  }
                },
                "feature" : {
                  "type" : "Some",
                  "value" : {
                    "type" : "Name",
                    "name" : ["tcs", "tcp", "tempSensor", "ports_tempChanged"],
                    "pos" : {
                      "type" : "Some",
                      "value" : {
                        "type" : "Position",
                        "uriOpt" : {
                          "type" : "Some",
                          "value" : "\/temp-control\/TempControlAadl.sysml"
                        },
                        "beginLine" : 37,
                        "beginColumn" : 4,
                        "endLine" : 37,
                        "endColumn" : 27,
                        "offset" : 1220,
                        "length" : 23
                      }
                    }
                  }
                },
                "direction" : {
                  "type" : "Some",
                  "value" : {
                    "type" : "Direction",
                    "value" : "Out"
                  }
                }
              },
              "dst" : {
                "type" : "EndPoint",
                "component" : {
                  "type" : "Name",
                  "name" : ["tcs", "tcp", "tempControl"],
                  "pos" : {
                    "type" : "Some",
                    "value" : {
                      "type" : "Position",
                      "uriOpt" : {
                        "type" : "Some",
                        "value" : "\/temp-control\/TempControlAadl.sysml"
                      },
                      "beginLine" : 19,
                      "beginColumn" : 3,
                      "endLine" : 19,
                      "endColumn" : 43,
                      "offset" : 436,
                      "length" : 40
                    }
                  }
                },
                "feature" : {
                  "type" : "Some",
                  "value" : {
                    "type" : "Name",
                    "name" : ["tcs", "tcp", "tempControl", "ports_tempChanged"],
                    "pos" : {
                      "type" : "Some",
                      "value" : {
                        "type" : "Position",
                        "uriOpt" : {
                          "type" : "Some",
                          "value" : "\/temp-control\/TempControlAadl.sysml"
                        },
                        "beginLine" : 51,
                        "beginColumn" : 4,
                        "endLine" : 51,
                        "endColumn" : 26,
                        "offset" : 1453,
                        "length" : 22
                      }
                    }
                  }
                },
                "direction" : {
                  "type" : "Some",
                  "value" : {
                    "type" : "Direction",
                    "value" : "In"
                  }
                }
              },
              "kind" : {
                "type" : "ConnectionKind",
                "value" : "Port"
              },
              "connectionRefs" : [
              ],
              "properties" : [
              ]
            },
            {
              "type" : "ConnectionInstance",
              "name" : {
                "type" : "Name",
                "name" : ["fake_it"],
                "pos" : {
                  "type" : "None"
                }
              },
              "src" : {
                "type" : "EndPoint",
                "component" : {
                  "type" : "Name",
                  "name" : ["tcs", "tcp", "tempControl"],
                  "pos" : {
                    "type" : "Some",
                    "value" : {
                      "type" : "Position",
                      "uriOpt" : {
                        "type" : "Some",
                        "value" : "\/temp-control\/TempControlAadl.sysml"
                      },
                      "beginLine" : 19,
                      "beginColumn" : 3,
                      "endLine" : 19,
                      "endColumn" : 43,
                      "offset" : 436,
                      "length" : 40
                    }
                  }
                },
                "feature" : {
                  "type" : "Some",
                  "value" : {
                    "type" : "Name",
                    "name" : ["tcs", "tcp", "tempControl", "ports_fanCmd"],
                    "pos" : {
                      "type" : "Some",
                      "value" : {
                        "type" : "Position",
                        "uriOpt" : {
                          "type" : "Some",
                          "value" : "\/temp-control\/TempControlAadl.sysml"
                        },
                        "beginLine" : 52,
                        "beginColumn" : 4,
                        "endLine" : 52,
                        "endColumn" : 34,
                        "offset" : 1479,
                        "length" : 30
                      }
                    }
                  }
                },
                "direction" : {
                  "type" : "Some",
                  "value" : {
                    "type" : "Direction",
                    "value" : "Out"
                  }
                }
              },
              "dst" : {
                "type" : "EndPoint",
                "component" : {
                  "type" : "Name",
                  "name" : ["tcs", "tcp", "fan"],
                  "pos" : {
                    "type" : "Some",
                    "value" : {
                      "type" : "Position",
                      "uriOpt" : {
                        "type" : "Some",
                        "value" : "\/temp-control\/TempControlAadl.sysml"
                      },
                      "beginLine" : 20,
                      "beginColumn" : 3,
                      "endLine" : 20,
                      "endColumn" : 27,
                      "offset" : 479,
                      "length" : 24
                    }
                  }
                },
                "feature" : {
                  "type" : "Some",
                  "value" : {
                    "type" : "Name",
                    "name" : ["tcs", "tcp", "fan", "ports_fanCmd"],
                    "pos" : {
                      "type" : "Some",
                      "value" : {
                        "type" : "Position",
                        "uriOpt" : {
                          "type" : "Some",
                          "value" : "\/temp-control\/TempControlAadl.sysml"
                        },
                        "beginLine" : 67,
                        "beginColumn" : 4,
                        "endLine" : 67,
                        "endColumn" : 33,
                        "offset" : 1738,
                        "length" : 29
                      }
                    }
                  }
                },
                "direction" : {
                  "type" : "Some",
                  "value" : {
                    "type" : "Direction",
                    "value" : "In"
                  }
                }
              },
              "kind" : {
                "type" : "ConnectionKind",
                "value" : "Port"
              },
              "connectionRefs" : [
              ],
              "properties" : [
              ]
            },
            {
              "type" : "ConnectionInstance",
              "name" : {
                "type" : "Name",
                "name" : ["fake_it"],
                "pos" : {
                  "type" : "None"
                }
              },
              "src" : {
                "type" : "EndPoint",
                "component" : {
                  "type" : "Name",
                  "name" : ["tcs", "tcp", "fan"],
                  "pos" : {
                    "type" : "Some",
                    "value" : {
                      "type" : "Position",
                      "uriOpt" : {
                        "type" : "Some",
                        "value" : "\/temp-control\/TempControlAadl.sysml"
                      },
                      "beginLine" : 20,
                      "beginColumn" : 3,
                      "endLine" : 20,
                      "endColumn" : 27,
                      "offset" : 479,
                      "length" : 24
                    }
                  }
                },
                "feature" : {
                  "type" : "Some",
                  "value" : {
                    "type" : "Name",
                    "name" : ["tcs", "tcp", "fan", "ports_fanAck"],
                    "pos" : {
                      "type" : "Some",
                      "value" : {
                        "type" : "Position",
                        "uriOpt" : {
                          "type" : "Some",
                          "value" : "\/temp-control\/TempControlAadl.sysml"
                        },
                        "beginLine" : 68,
                        "beginColumn" : 4,
                        "endLine" : 68,
                        "endColumn" : 34,
                        "offset" : 1771,
                        "length" : 30
                      }
                    }
                  }
                },
                "direction" : {
                  "type" : "Some",
                  "value" : {
                    "type" : "Direction",
                    "value" : "Out"
                  }
                }
              },
              "dst" : {
                "type" : "EndPoint",
                "component" : {
                  "type" : "Name",
                  "name" : ["tcs", "tcp", "tempControl"],
                  "pos" : {
                    "type" : "Some",
                    "value" : {
                      "type" : "Position",
                      "uriOpt" : {
                        "type" : "Some",
                        "value" : "\/temp-control\/TempControlAadl.sysml"
                      },
                      "beginLine" : 19,
                      "beginColumn" : 3,
                      "endLine" : 19,
                      "endColumn" : 43,
                      "offset" : 436,
                      "length" : 40
                    }
                  }
                },
                "feature" : {
                  "type" : "Some",
                  "value" : {
                    "type" : "Name",
                    "name" : ["tcs", "tcp", "tempControl", "ports_fanAck"],
                    "pos" : {
                      "type" : "Some",
                      "value" : {
                        "type" : "Position",
                        "uriOpt" : {
                          "type" : "Some",
                          "value" : "\/temp-control\/TempControlAadl.sysml"
                        },
                        "beginLine" : 53,
                        "beginColumn" : 4,
                        "endLine" : 53,
                        "endColumn" : 33,
                        "offset" : 1513,
                        "length" : 29
                      }
                    }
                  }
                },
                "direction" : {
                  "type" : "Some",
                  "value" : {
                    "type" : "Direction",
                    "value" : "In"
                  }
                }
              },
              "kind" : {
                "type" : "ConnectionKind",
                "value" : "Port"
              },
              "connectionRefs" : [
              ],
              "properties" : [
              ]
            },
            {
              "type" : "ConnectionInstance",
              "name" : {
                "type" : "Name",
                "name" : ["fake_it"],
                "pos" : {
                  "type" : "None"
                }
              },
              "src" : {
                "type" : "EndPoint",
                "component" : {
                  "type" : "Name",
                  "name" : ["tcs", "tcp", "opInterface"],
                  "pos" : {
                    "type" : "Some",
                    "value" : {
                      "type" : "Position",
                      "uriOpt" : {
                        "type" : "Some",
                        "value" : "\/temp-control\/TempControlAadl.sysml"
                      },
                      "beginLine" : 21,
                      "beginColumn" : 3,
                      "endLine" : 21,
                      "endColumn" : 49,
                      "offset" : 506,
                      "length" : 46
                    }
                  }
                },
                "feature" : {
                  "type" : "Some",
                  "value" : {
                    "type" : "Name",
                    "name" : ["tcs", "tcp", "opInterface", "ports_setPoint"],
                    "pos" : {
                      "type" : "Some",
                      "value" : {
                        "type" : "Position",
                        "uriOpt" : {
                          "type" : "Some",
                          "value" : "\/temp-control\/TempControlAadl.sysml"
                        },
                        "beginLine" : 82,
                        "beginColumn" : 4,
                        "endLine" : 82,
                        "endColumn" : 41,
                        "offset" : 2023,
                        "length" : 37
                      }
                    }
                  }
                },
                "direction" : {
                  "type" : "Some",
                  "value" : {
                    "type" : "Direction",
                    "value" : "Out"
                  }
                }
              },
              "dst" : {
                "type" : "EndPoint",
                "component" : {
                  "type" : "Name",
                  "name" : ["tcs", "tcp", "tempControl"],
                  "pos" : {
                    "type" : "Some",
                    "value" : {
                      "type" : "Position",
                      "uriOpt" : {
                        "type" : "Some",
                        "value" : "\/temp-control\/TempControlAadl.sysml"
                      },
                      "beginLine" : 19,
                      "beginColumn" : 3,
                      "endLine" : 19,
                      "endColumn" : 43,
                      "offset" : 436,
                      "length" : 40
                    }
                  }
                },
                "feature" : {
                  "type" : "Some",
                  "value" : {
                    "type" : "Name",
                    "name" : ["tcs", "tcp", "tempControl", "ports_setPoint"],
                    "pos" : {
                      "type" : "Some",
                      "value" : {
                        "type" : "Position",
                        "uriOpt" : {
                          "type" : "Some",
                          "value" : "\/temp-control\/TempControlAadl.sysml"
                        },
                        "beginLine" : 54,
                        "beginColumn" : 4,
                        "endLine" : 54,
                        "endColumn" : 40,
                        "offset" : 1546,
                        "length" : 36
                      }
                    }
                  }
                },
                "direction" : {
                  "type" : "Some",
                  "value" : {
                    "type" : "Direction",
                    "value" : "In"
                  }
                }
              },
              "kind" : {
                "type" : "ConnectionKind",
                "value" : "Port"
              },
              "connectionRefs" : [
              ],
              "properties" : [
              ]
            }
          ],
          "properties" : [
          ],
          "flows" : [
          ],
          "modes" : [
          ],
          "annexes" : [
          ],
          "uriFrag" : ""
        }
      ],
      "connections" : [
      ],
      "connectionInstances" : [
      ],
      "properties" : [
      ],
      "flows" : [
      ],
      "modes" : [
      ],
      "annexes" : [
      ],
      "uriFrag" : ""
    }
  ],
  "annexLib" : [
  ],
  "dataComponents" : [
    {
      "type" : "Component",
      "identifier" : {
        "type" : "Name",
        "name" : [],
        "pos" : {
          "type" : "None"
        }
      },
      "category" : {
        "type" : "ComponentCategory",
        "value" : "Data"
      },
      "classifier" : {
        "type" : "Some",
        "value" : {
          "type" : "Classifier",
          "name" : "ScalarValues::Integer"
        }
      },
      "features" : [
      ],
      "subComponents" : [
      ],
      "connections" : [
      ],
      "connectionInstances" : [
      ],
      "properties" : [
      ],
      "flows" : [
      ],
      "modes" : [
      ],
      "annexes" : [
      ],
      "uriFrag" : "fake uri tag that's only needed if AWAS is invoked"
    },
    {
      "type" : "Component",
      "identifier" : {
        "type" : "Name",
        "name" : [],
        "pos" : {
          "type" : "None"
        }
      },
      "category" : {
        "type" : "ComponentCategory",
        "value" : "Data"
      },
      "classifier" : {
        "type" : "Some",
        "value" : {
          "type" : "Classifier",
          "name" : "TempControlAadl::TempUnit"
        }
      },
      "features" : [
      ],
      "subComponents" : [
      ],
      "connections" : [
      ],
      "connectionInstances" : [
      ],
      "properties" : [
        {
          "type" : "Property",
          "name" : {
            "type" : "Name",
            "name" : ["Data_Model::Data_Representation"],
            "pos" : {
              "type" : "None"
            }
          },
          "propertyValues" : [
            {
              "type" : "ValueProp",
              "value" : "Enum"
            }
          ],
          "appliesTo" : [
          ]
        },
        {
          "type" : "Property",
          "name" : {
            "type" : "Name",
            "name" : ["Data_Model::Enumerators"],
            "pos" : {
              "type" : "None"
            }
          },
          "propertyValues" : [
            {
              "type" : "ValueProp",
              "value" : "Fahrenheit"
            },
            {
              "type" : "ValueProp",
              "value" : "Celsius"
            },
            {
              "type" : "ValueProp",
              "value" : "Kelvin"
            }
          ],
          "appliesTo" : [
          ]
        }
      ],
      "flows" : [
      ],
      "modes" : [
      ],
      "annexes" : [
      ],
      "uriFrag" : "fake uri tag that's only needed if AWAS is invoked"
    },
    {
      "type" : "Component",
      "identifier" : {
        "type" : "Name",
        "name" : [],
        "pos" : {
          "type" : "None"
        }
      },
      "category" : {
        "type" : "ComponentCategory",
        "value" : "Data"
      },
      "classifier" : {
        "type" : "Some",
        "value" : {
          "type" : "Classifier",
          "name" : "TempControlAadl::Temperature"
        }
      },
      "features" : [
      ],
      "subComponents" : [
      ],
      "connections" : [
      ],
      "connectionInstances" : [
      ],
      "properties" : [
      ],
      "flows" : [
      ],
      "modes" : [
      ],
      "annexes" : [
      ],
      "uriFrag" : "fake uri tag that's only needed if AWAS is invoked"
    },
    {
      "type" : "Component",
      "identifier" : {
        "type" : "Name",
        "name" : [],
        "pos" : {
          "type" : "None"
        }
      },
      "category" : {
        "type" : "ComponentCategory",
        "value" : "Data"
      },
      "classifier" : {
        "type" : "Some",
        "value" : {
          "type" : "Classifier",
          "name" : "TempControlAadl::FanCmd"
        }
      },
      "features" : [
      ],
      "subComponents" : [
      ],
      "connections" : [
      ],
      "connectionInstances" : [
      ],
      "properties" : [
        {
          "type" : "Property",
          "name" : {
            "type" : "Name",
            "name" : ["Data_Model::Data_Representation"],
            "pos" : {
              "type" : "None"
            }
          },
          "propertyValues" : [
            {
              "type" : "ValueProp",
              "value" : "Enum"
            }
          ],
          "appliesTo" : [
          ]
        },
        {
          "type" : "Property",
          "name" : {
            "type" : "Name",
            "name" : ["Data_Model::Enumerators"],
            "pos" : {
              "type" : "None"
            }
          },
          "propertyValues" : [
            {
              "type" : "ValueProp",
              "value" : "On"
            },
            {
              "type" : "ValueProp",
              "value" : "Off"
            }
          ],
          "appliesTo" : [
          ]
        }
      ],
      "flows" : [
      ],
      "modes" : [
      ],
      "annexes" : [
      ],
      "uriFrag" : "fake uri tag that's only needed if AWAS is invoked"
    },
    {
      "type" : "Component",
      "identifier" : {
        "type" : "Name",
        "name" : [],
        "pos" : {
          "type" : "None"
        }
      },
      "category" : {
        "type" : "ComponentCategory",
        "value" : "Data"
      },
      "classifier" : {
        "type" : "Some",
        "value" : {
          "type" : "Classifier",
          "name" : "TempControlAadl::FanAck"
        }
      },
      "features" : [
      ],
      "subComponents" : [
      ],
      "connections" : [
      ],
      "connectionInstances" : [
      ],
      "properties" : [
        {
          "type" : "Property",
          "name" : {
            "type" : "Name",
            "name" : ["Data_Model::Data_Representation"],
            "pos" : {
              "type" : "None"
            }
          },
          "propertyValues" : [
            {
              "type" : "ValueProp",
              "value" : "Enum"
            }
          ],
          "appliesTo" : [
          ]
        },
        {
          "type" : "Property",
          "name" : {
            "type" : "Name",
            "name" : ["Data_Model::Enumerators"],
            "pos" : {
              "type" : "None"
            }
          },
          "propertyValues" : [
            {
              "type" : "ValueProp",
              "value" : "Ok"
            },
            {
              "type" : "ValueProp",
              "value" : "Error"
            }
          ],
          "appliesTo" : [
          ]
        }
      ],
      "flows" : [
      ],
      "modes" : [
      ],
      "annexes" : [
      ],
      "uriFrag" : "fake uri tag that's only needed if AWAS is invoked"
    }
  ]
}